{
	"Version_Installed": "1.0.2",
	"Version_Type": "Optional",
	"UsersMin": "150",
	"Users": "300",
	"Message": "Waheguru ji ka khalsa!!\nWaheguru ji ki fateh!!\nNew Gurbani added in new version  &lt; ",
	"MainActivity": "mMglvwr, 26 jyT (sMmq 553 nwnkSwhI) iqlµg bwxI Bgqw kI kbIr jI &lt;> siqgur pRswid ] byd kqyb iePqrw BweI idl kw iPkru n jwie ] tuku dmu krwrI jau krhu hwijr hjUir Kudwie ]1] bMdy Koju idl hr roj nw iPru pryswnI mwih ] ieh ju dunIAw ishru mylw dsqgIrI nwih ]1] rhwau ]",
	"AlertDetail": "<font color='#ff9933'>mMglvwr, 26 jyT (sMmq 553 nwnkSwhI)</font> <br/><font color='#38777A'>iqlµg bwxI Bgqw kI kbIr jI</font>&lt;> siqgur pRswid ] byd kqyb iePqrw BweI idl kw iPkru n jwie ] tuku dmu krwrI jau krhu hwijr hjUir Kudwie ]1] bMdy Koju idl hr roj nw iPru pryswnI mwih ] ieh ju dunIAw ishru mylw dsqgIrI nwih ]1] rhwau ]"
}
